bbspinner/__init__.py
bbspinner-0.0.1.dist-info/METADATA
bbspinner-0.0.1.dist-info/WHEEL
bbspinner-0.0.1.dist-info/top_level.txt
bbspinner-0.0.1.dist-info/RECORD
